setup.py
curvy/__init__.py
curvy/basic_plotter.py
curvy/interactive_plotter.py
curvy.egg-info/PKG-INFO
curvy.egg-info/SOURCES.txt
curvy.egg-info/dependency_links.txt
curvy.egg-info/not-zip-safe
curvy.egg-info/top_level.txt