Metadata-Version: 2.1
Name: curvy
Version: 0.1.0
Summary: Plot model performance
Home-page: https://github.com/KimaniKibuthu/curvy
Author: br-AI-niac
Author-email: kimanikibuthu@gmail.com
License: MIT
Platform: UNKNOWN
